<?xml version="1.0" encoding="utf-8"?>
<ArrayOfDependency>
  <Dependency>
    <Id>4386</Id>
    <PreTask>2116</PreTask>
    <CurrTask>2117</CurrTask>
  </Dependency>
  <Dependency>
    <Id>4387</Id>
    <PreTask>2116</PreTask>
    <CurrTask>2118</CurrTask>
  </Dependency>
  <Dependency>
    <Id>4388</Id>
    <PreTask>2117</PreTask>
    <CurrTask>2121</CurrTask>
  </Dependency>
  <Dependency>
    <Id>4389</Id>
    <PreTask>2143</PreTask>
    <CurrTask>2121</CurrTask>
  </Dependency>
  <Dependency>
    <Id>4396</Id>
    <PreTask>2135</PreTask>
    <CurrTask>2122</CurrTask>
  </Dependency>
  <Dependency>
    <Id>4397</Id>
    <PreTask>2136</PreTask>
    <CurrTask>2122</CurrTask>
  </Dependency>
  <Dependency>
    <Id>4398</Id>
    <PreTask>2138</PreTask>
    <CurrTask>2122</CurrTask>
  </Dependency>
  <Dependency>
    <Id>4399</Id>
    <PreTask>2119</PreTask>
    <CurrTask>2123</CurrTask>
  </Dependency>
  <Dependency>
    <Id>4400</Id>
    <PreTask>2131</PreTask>
    <CurrTask>2123</CurrTask>
  </Dependency>
  <Dependency>
    <Id>4401</Id>
    <PreTask>2140</PreTask>
    <CurrTask>2124</CurrTask>
  </Dependency>
  <Dependency>
    <Id>4402</Id>
    <PreTask>2117</PreTask>
    <CurrTask>2125</CurrTask>
  </Dependency>
  <Dependency>
    <Id>4403</Id>
    <PreTask>2117</PreTask>
    <CurrTask>2126</CurrTask>
  </Dependency>
  <Dependency>
    <Id>4404</Id>
    <PreTask>2116</PreTask>
    <CurrTask>2127</CurrTask>
  </Dependency>
  <Dependency>
    <Id>4405</Id>
    <PreTask>2117</PreTask>
    <CurrTask>2128</CurrTask>
  </Dependency>
  <Dependency>
    <Id>4406</Id>
    <PreTask>2120</PreTask>
    <CurrTask>2129</CurrTask>
  </Dependency>
  <Dependency>
    <Id>4407</Id>
    <PreTask>2116</PreTask>
    <CurrTask>2129</CurrTask>
  </Dependency>
  <Dependency>
    <Id>4408</Id>
    <PreTask>2139</PreTask>
    <CurrTask>2129</CurrTask>
  </Dependency>
  <Dependency>
    <Id>4409</Id>
    <PreTask>2134</PreTask>
    <CurrTask>2130</CurrTask>
  </Dependency>
  <Dependency>
    <Id>4410</Id>
    <PreTask>2127</PreTask>
    <CurrTask>2132</CurrTask>
  </Dependency>
  <Dependency>
    <Id>4411</Id>
    <PreTask>2134</PreTask>
    <CurrTask>2132</CurrTask>
  </Dependency>
  <Dependency>
    <Id>4412</Id>
    <PreTask>2131</PreTask>
    <CurrTask>2132</CurrTask>
  </Dependency>
  <Dependency>
    <Id>4413</Id>
    <PreTask>2120</PreTask>
    <CurrTask>2133</CurrTask>
  </Dependency>
  <Dependency>
    <Id>4414</Id>
    <PreTask>2116</PreTask>
    <CurrTask>2135</CurrTask>
  </Dependency>
  <Dependency>
    <Id>4415</Id>
    <PreTask>2116</PreTask>
    <CurrTask>2135</CurrTask>
  </Dependency>
  <Dependency>
    <Id>4416</Id>
    <PreTask>2120</PreTask>
    <CurrTask>2137</CurrTask>
  </Dependency>
  <Dependency>
    <Id>4417</Id>
    <PreTask>2116</PreTask>
    <CurrTask>2137</CurrTask>
  </Dependency>
  <Dependency>
    <Id>4418</Id>
    <PreTask>2139</PreTask>
    <CurrTask>2137</CurrTask>
  </Dependency>
  <Dependency>
    <Id>4419</Id>
    <PreTask>2137</PreTask>
    <CurrTask>2138</CurrTask>
  </Dependency>
  <Dependency>
    <Id>4420</Id>
    <PreTask>2123</PreTask>
    <CurrTask>2141</CurrTask>
  </Dependency>
  <Dependency>
    <Id>4421</Id>
    <PreTask>2132</PreTask>
    <CurrTask>2141</CurrTask>
  </Dependency>
  <Dependency>
    <Id>4422</Id>
    <PreTask>2128</PreTask>
    <CurrTask>2141</CurrTask>
  </Dependency>
  <Dependency>
    <Id>4423</Id>
    <PreTask>2118</PreTask>
    <CurrTask>2141</CurrTask>
  </Dependency>
  <Dependency>
    <Id>4424</Id>
    <PreTask>2123</PreTask>
    <CurrTask>2142</CurrTask>
  </Dependency>
  <Dependency>
    <Id>4425</Id>
    <PreTask>2122</PreTask>
    <CurrTask>2142</CurrTask>
  </Dependency>
  <Dependency>
    <Id>4426</Id>
    <PreTask>2132</PreTask>
    <CurrTask>2142</CurrTask>
  </Dependency>
  <Dependency>
    <Id>4427</Id>
    <PreTask>2127</PreTask>
    <CurrTask>2142</CurrTask>
  </Dependency>
  <Dependency>
    <Id>4428</Id>
    <PreTask>2143</PreTask>
    <CurrTask>2144</CurrTask>
  </Dependency>
  <Dependency>
    <Id>4429</Id>
    <PreTask>2134</PreTask>
    <CurrTask>2145</CurrTask>
  </Dependency>
  <Dependency>
    <Id>4430</Id>
    <PreTask>2131</PreTask>
    <CurrTask>2145</CurrTask>
  </Dependency>
  <Dependency>
    <Id>4431</Id>
    <PreTask>2119</PreTask>
    <CurrTask>2145</CurrTask>
  </Dependency>
</ArrayOfDependency>